llm_queue_manager/__init__.py
llm_queue_manager/config/__init__.py
llm_queue_manager/config/redis_config.py
llm_queue_manager/core/__init__.py
llm_queue_manager/core/batch_processor.py
llm_queue_manager/core/models.py
llm_queue_manager/core/queue_manager.py
llm_queue_manager/core/token_estimator.py
llm_queue_manager/processors/__init__.py
llm_queue_manager/processors/base.py
llm_queue_manager/processors/examples/__init__.py
llm_queue_manager/processors/examples/bedrock_processor.py
llm_queue_manager/processors/examples/openai_processor.py
llm_queue_manager/utils/__init__.py
llm_queue_manager/utils/helpers.py
llm_queue_task_manager-0.1.3.dist-info/licenses/LICENSE
llm_queue_task_manager-0.1.3.dist-info/METADATA
llm_queue_task_manager-0.1.3.dist-info/WHEEL
llm_queue_task_manager-0.1.3.dist-info/top_level.txt
llm_queue_task_manager-0.1.3.dist-info/RECORD
