Metadata-Version: 2.4
Name: llm-queue-task-manager
Version: 0.1.3
Summary: A Redis-based queue task manager for LLM processing with intelligent token budget management
Author-email: Aryaman Gurjar <aryamangurjar6@gmail.com>
License: MIT
Project-URL: Homepage, https://github.com/yourusername/llm-queue-task-manager
Project-URL: Repository, https://github.com/yourusername/llm-queue-task-manager
Project-URL: Issues, https://github.com/yourusername/llm-queue-task-manager/issues
Keywords: llm,queue,redis,task-manager,token-management,ai
Classifier: Development Status :: 4 - Beta
Classifier: Intended Audience :: Developers
Classifier: License :: OSI Approved :: MIT License
Classifier: Programming Language :: Python :: 3
Classifier: Programming Language :: Python :: 3.8
Classifier: Programming Language :: Python :: 3.9
Classifier: Programming Language :: Python :: 3.10
Classifier: Programming Language :: Python :: 3.11
Classifier: Programming Language :: Python :: 3.12
Classifier: Topic :: Software Development :: Libraries :: Python Modules
Classifier: Topic :: System :: Distributed Computing
Classifier: Topic :: Scientific/Engineering :: Artificial Intelligence
Requires-Python: >=3.8
License-File: LICENSE
Requires-Dist: redis>=4.0.0
Requires-Dist: pydantic>=2.0.0
Provides-Extra: fastapi
Requires-Dist: fastapi>=0.100.0; extra == "fastapi"
Requires-Dist: uvicorn>=0.20.0; extra == "fastapi"
Provides-Extra: aws
Requires-Dist: boto3>=1.26.0; extra == "aws"
Requires-Dist: botocore>=1.29.0; extra == "aws"
Provides-Extra: openai
Requires-Dist: openai>=1.0.0; extra == "openai"
Provides-Extra: all
Requires-Dist: fastapi>=0.100.0; extra == "all"
Requires-Dist: uvicorn>=0.20.0; extra == "all"
Requires-Dist: boto3>=1.26.0; extra == "all"
Requires-Dist: botocore>=1.29.0; extra == "all"
Requires-Dist: openai>=1.0.0; extra == "all"
Provides-Extra: dev
Requires-Dist: pytest>=7.0.0; extra == "dev"
Requires-Dist: pytest-asyncio>=0.21.0; extra == "dev"
Requires-Dist: black>=23.0.0; extra == "dev"
Requires-Dist: isort>=5.12.0; extra == "dev"
Requires-Dist: mypy>=1.0.0; extra == "dev"
Dynamic: license-file
